lyy_life/__init__.py
lyy_life/life.py
lyy_life-0.0.1.dist-info/LICENSE
lyy_life-0.0.1.dist-info/METADATA
lyy_life-0.0.1.dist-info/WHEEL
lyy_life-0.0.1.dist-info/entry_points.txt
lyy_life-0.0.1.dist-info/top_level.txt
lyy_life-0.0.1.dist-info/RECORD
