Metadata-Version: 2.1
Name: lyy-life
Version: 0.0.1
Summary: this is my life.
Home-page: https://github.com/yongyaoli/lyy_life
Author: yixin2009
Author-email: 731969968@qq.com
License: MIT
Keywords: python liyy life
Platform: UNKNOWN
Classifier: Operating System :: OS Independent
Classifier: Topic :: Software Development
Classifier: Programming Language :: Python :: 3
Classifier: Programming Language :: Python :: Implementation :: PyPy
Requires-Python: >=3.5
Provides-Extra: test
